{
  "project_info": {
    "project_number": "218204947232",
    "firebase_url": "https://finesse-e9796.firebaseio.com",
    "project_id": "finesse-e9796",
    "storage_bucket": "finesse-e9796.appspot.com"
  },
  "client": [
    {
      "client_info": {
        "mobilesdk_app_id": "1:218204947232:android:cb924e1bc9d52e57",
        "android_client_info": {
          "package_name": "com.example.elijahc.finesse"
        }
      },
      "oauth_client": [
        {
          "client_id": "218204947232-fbb8509o929g69srd8s4ot4bghu4di0v.apps.googleusercontent.com",
          "client_type": 1,
          "android_info": {
            "package_name": "com.example.elijahc.finesse",
            "certificate_hash": "38355ce4a733175cb9f92c1ee746c3a2eaa33441"
          }
        },
        {
          "client_id": "218204947232-jligf42tobs982oqnf55btk77krenelm.apps.googleusercontent.com",
          "client_type": 3
        }
      ],
      "api_key": [
        {
          "current_key": "AIzaSyA1sGAMRaVMA-0cPvXu6y93c5QnTydPR-A"
        }
      ],
      "services": {
        "analytics_service": {
          "status": 1
        },
        "appinvite_service": {
          "status": 2,
          "other_platform_oauth_client": [
            {
              "client_id": "218204947232-jligf42tobs982oqnf55btk77krenelm.apps.googleusercontent.com",
              "client_type": 3
            }
          ]
        },
        "ads_service": {
          "status": 2
        }
      }
    },
    {
      "client_info": {
        "mobilesdk_app_id": "1:218204947232:android:4b8aa935d676ee79",
        "android_client_info": {
          "package_name": "com.osalaam.immersionproj2"
        }
      },
      "oauth_client": [
        {
          "client_id": "218204947232-s2qgd3vaqn3lqg79aufprm4es7mmv67e.apps.googleusercontent.com",
          "client_type": 1,
          "android_info": {
            "package_name": "com.osalaam.immersionproj2",
            "certificate_hash": "38355ce4a733175cb9f92c1ee746c3a2eaa33441"
          }
        },
        {
          "client_id": "218204947232-jligf42tobs982oqnf55btk77krenelm.apps.googleusercontent.com",
          "client_type": 3
        }
      ],
      "api_key": [
        {
          "current_key": "AIzaSyA1sGAMRaVMA-0cPvXu6y93c5QnTydPR-A"
        }
      ],
      "services": {
        "analytics_service": {
          "status": 1
        },
        "appinvite_service": {
          "status": 2,
          "other_platform_oauth_client": [
            {
              "client_id": "218204947232-jligf42tobs982oqnf55btk77krenelm.apps.googleusercontent.com",
              "client_type": 3
            }
          ]
        },
        "ads_service": {
          "status": 2
        }
      }
    }
  ],
  "configuration_version": "1"
}